Metadata-Version: 2.2
Name: custom-manytask-checker
Version: 2.0.5.dev0
Summary: Students' solution checker
Author-email: Yegor Podlesov <ypodlesov@gmail.com>
Classifier: Development Status :: 4 - Beta
Classifier: Typing :: Typed
Classifier: Intended Audience :: Education
Classifier: Topic :: Education
Classifier: Topic :: Education :: Testing
Classifier: Programming Language :: Python :: 3 :: Only
Classifier: Programming Language :: Python :: 3.9
Classifier: Programming Language :: Python :: 3.10
Classifier: Programming Language :: Python :: 3.11
Classifier: Programming Language :: Python :: 3.12
Requires-Python: >=3.9
Requires-Dist: Jinja2<4.0.0,>=3.0.0
Requires-Dist: PyYAML<7.0.0,>=5.0.0
Requires-Dist: click<9.0,>=8.0
Requires-Dist: python-gitlab<5.0.0,>=3.0.0
Requires-Dist: pydantic<3.0.0,>=2.0.0
Requires-Dist: rich<14.0.0,>=13.0.0
Requires-Dist: requests<3.0.0,>=2.20.0
Requires-Dist: pytz<2023.4,>=2022.0; python_version < "3.9"
Requires-Dist: urllib3<3.0.0,>=2.0.0
Requires-Dist: GitPython<4.0.0,>=3.0.0
Provides-Extra: test
Requires-Dist: pytest<9.0.0,>=6.0.0; extra == "test"
Requires-Dist: pytest-cov<6.0.0,>=4.0.0; extra == "test"
Requires-Dist: pytest-mock<4.0.0,>=3.0.0; extra == "test"
Requires-Dist: requests-mock<2.0.0,>=1.0.0; extra == "test"
Requires-Dist: black==23.12.1; extra == "test"
Requires-Dist: mypy>=1.0.0; extra == "test"
Requires-Dist: flake8<8.0.0,>=4.0.0; extra == "test"
Requires-Dist: isort<7.0.0,>=5.0.0; extra == "test"
Requires-Dist: ruff==0.4.4; extra == "test"
Requires-Dist: types-requests<3.0.0,>=2.20.0; extra == "test"
Requires-Dist: types-PyYAML<7.0.0,>=6.0.0; extra == "test"
Requires-Dist: wheel>=0.40.0; extra == "test"
Requires-Dist: pre-commit<4.0.0,>=3.0.0; extra == "test"
Provides-Extra: docs
Requires-Dist: mike<3.0.0,>=1.1.0; extra == "docs"
Requires-Dist: mkdocs<2.0.0,>=1.4.0; extra == "docs"
Requires-Dist: mkdocs-autorefs==1.0.1; extra == "docs"
Requires-Dist: mkdocs-click>=0.8.0; extra == "docs"
Requires-Dist: mkdocs-include-markdown-plugin<7.0.0,>=4.0.0; extra == "docs"
Requires-Dist: mkdocs-material<10.0.0,>=9.0.0; extra == "docs"
Requires-Dist: mkdocs-material-extensions==1.3.1; extra == "docs"
Requires-Dist: mkdocstrings[python]==0.25.1; extra == "docs"
Requires-Dist: mkdocs-mermaid2-plugin==1.1.1; extra == "docs"
